MANIFEST.in
README.md
cloudcracker.py
setup.py
python_cloudcracker.egg-info/PKG-INFO
python_cloudcracker.egg-info/SOURCES.txt
python_cloudcracker.egg-info/dependency_links.txt
python_cloudcracker.egg-info/top_level.txt